aerial_contamination.py
aerial_contamination-0.0.1.dist-info/METADATA
aerial_contamination-0.0.1.dist-info/WHEEL
aerial_contamination-0.0.1.dist-info/entry_points.txt
aerial_contamination-0.0.1.dist-info/top_level.txt
aerial_contamination-0.0.1.dist-info/RECORD
