Metadata-Version: 2.1
Name: aerial-contamination
Version: 0.0.1
Summary: A package for counting bugs
Home-page: https://github.com/HAKU0312/aerial-contamination
Author: YE BOWEN
Author-email: s1922037@stu.musashino-u.ac.jp
License: UNKNOWN
Project-URL: Bug Tracker, https://github.com/HAKU0312/aerial-contamination
Platform: UNKNOWN
Classifier: Programming Language :: Python :: 3
Classifier: License :: OSI Approved :: MIT License
Classifier: Operating System :: OS Independent
Requires-Python: >=3.6
